cdisc_data_providers/__init__.py
cdisc_data_providers/sdtm_data_provider.py
cdisc_model_managers/__init__.py
cdisc_model_managers/cdisc_api.py
cdisc_model_managers/cdisc_model_manager.py
cdisc_model_managers/cdisc_standard_loader.py
neo4cdisc-1.0.5.3.dist-info/LICENSE
neo4cdisc-1.0.5.3.dist-info/METADATA
neo4cdisc-1.0.5.3.dist-info/WHEEL
neo4cdisc-1.0.5.3.dist-info/top_level.txt
neo4cdisc-1.0.5.3.dist-info/RECORD
