Metadata-Version: 2.1
Name: neo4cdisc
Version: 1.0.5.3
Summary: Clinical Linked Data: Example of loading the FDA CDISC pilot study into Neo4J using the tab2neo python package
Home-page: UNKNOWN
Author: Alexey Kuznetsov
License: Apache License
Requires-Dist: tab2neo (==1.3.0.3)
